weather_one/__init__.py
weather_one/cli.py
weather_one-0.1.0.dist-info/METADATA
weather_one-0.1.0.dist-info/WHEEL
weather_one-0.1.0.dist-info/RECORD
